compaction/__init__.py
compaction/_version.py
compaction/cli.py
compaction/compaction.py
compaction/landlab.py
tests/__init__.py
tests/test_cli.py
tests/test_compaction.py
tests/test_component.py
compaction-0.1.0b0.dist-info/LICENSE
compaction-0.1.0b0.dist-info/METADATA
compaction-0.1.0b0.dist-info/WHEEL
compaction-0.1.0b0.dist-info/entry_points.txt
compaction-0.1.0b0.dist-info/top_level.txt
compaction-0.1.0b0.dist-info/RECORD
