Metadata-Version: 2.1
Name: compaction
Version: 0.1.0b0
Summary: Compact sediment
Home-page: http://csdms.colorado.edu
Author: Eric Hutton
Author-email: huttone@colorado.edu
License: UNKNOWN
Platform: UNKNOWN
Classifier: Intended Audience :: Science/Research
Classifier: License :: OSI Approved :: MIT License
Classifier: Operating System :: OS Independent
Classifier: Programming Language :: Python :: 3.6
Classifier: Programming Language :: Python :: 3.7
Classifier: Topic :: Scientific/Engineering :: Physics
Requires-Dist: click
Requires-Dist: landlab
Requires-Dist: numpy
Requires-Dist: pandas
Requires-Dist: pyyaml
Requires-Dist: scipy
